README
setup.cfg
setup.py
bin/ia_query_client
interanasdk/__init__.py
interanasdk/interana_query_sdk.py
interanasdk.egg-info/PKG-INFO
interanasdk.egg-info/SOURCES.txt
interanasdk.egg-info/dependency_links.txt
interanasdk.egg-info/requires.txt
interanasdk.egg-info/top_level.txt