Metadata-Version: 1.1
Name: interanasdk
Version: 0.0.2
Summary: Interana SDK
Home-page: https://github.com/Interana/interana-sdk
Author: Sachin Holla
Author-email: sachin@interana.com
License: UNKNOWN
Download-URL: https://github.com/Interana/interana-sdk/archive/0.0.2.tar.gz
Keywords: interana,sdk,query-api
Platform: UNKNOWN
